docs/SPX_PYTHON_LLM.md
spx_python/__init__.py
spx_python/client.py
spx_python/faults.py
spx_python/helpers.py
spx_python/pytest_logging.py
spx_python/transport.py
spx_python/unittest_logging.py
spx_python-1.0.0.dist-info/METADATA
spx_python-1.0.0.dist-info/WHEEL
spx_python-1.0.0.dist-info/licenses/LICENSE
spx_python-1.0.0.dist-info/RECORD
