Metadata-Version: 2.4
Name: spx-python
Version: 1.0.0
Summary: A Python library for managing spx server.
License: MIT
License-File: LICENSE
Author: Aleksander Stanik
Author-email: aleksander.stanik@hammerheadesengineers.com
Requires-Python: >=3.9,<4.0
Classifier: License :: OSI Approved :: MIT License
Classifier: Programming Language :: Python :: 3
Classifier: Programming Language :: Python :: 3.9
Classifier: Programming Language :: Python :: 3.10
Classifier: Programming Language :: Python :: 3.11
Classifier: Programming Language :: Python :: 3.12
Classifier: Programming Language :: Python :: 3.13
Classifier: Programming Language :: Python :: 3.14
Requires-Dist: requests
